CONTRIBUTING.rst
LICENSE
MANIFEST.in
README.rst
setup.cfg
setup.py
pykulersky/__init__.py
pykulersky/cli.py
pykulersky/discovery.py
pykulersky/exceptions.py
pykulersky/light.py
pykulersky.egg-info/PKG-INFO
pykulersky.egg-info/SOURCES.txt
pykulersky.egg-info/dependency_links.txt
pykulersky.egg-info/entry_points.txt
pykulersky.egg-info/not-zip-safe
pykulersky.egg-info/requires.txt
pykulersky.egg-info/top_level.txt
tests/__init__.py
tests/conftest.py
tests/test_discovery.py
tests/test_light.py