Metadata-Version: 2.2
Name: pykulersky
Version: 0.6.0
Summary: Library to control Brightech Kuler Sky Bluetooth LED smart lamps
Home-page: https://github.com/emlove/pykulersky
Author: Emily Love Watson
Author-email: emily@emlove.me
License: Apache Software License 2.0
Keywords: pykulersky
Classifier: Development Status :: 4 - Beta
Classifier: Intended Audience :: Developers
Classifier: License :: OSI Approved :: Apache Software License
Classifier: Natural Language :: English
Classifier: Programming Language :: Python :: 3
Classifier: Programming Language :: Python :: 3.9
Classifier: Programming Language :: Python :: 3.10
Classifier: Programming Language :: Python :: 3.11
Classifier: Programming Language :: Python :: 3.12
Classifier: Programming Language :: Python :: 3.13
Requires-Python: >=3.6
License-File: LICENSE
Requires-Dist: Click>=7.0
Requires-Dist: bleak>=1.0.1
Dynamic: author
Dynamic: author-email
Dynamic: classifier
Dynamic: description
Dynamic: home-page
Dynamic: keywords
Dynamic: license
Dynamic: requires-dist
Dynamic: requires-python
Dynamic: summary
